MANIFEST.in
README.md
setup.py
3rd-party/parallel-hashmap/LICENSE
3rd-party/parallel-hashmap/README.md
3rd-party/parallel-hashmap/parallel_hashmap/btree.h
3rd-party/parallel-hashmap/parallel_hashmap/meminfo.h
3rd-party/parallel-hashmap/parallel_hashmap/phmap.h
3rd-party/parallel-hashmap/parallel_hashmap/phmap_base.h
3rd-party/parallel-hashmap/parallel_hashmap/phmap_bits.h
3rd-party/parallel-hashmap/parallel_hashmap/phmap_config.h
3rd-party/parallel-hashmap/parallel_hashmap/phmap_dump.h
3rd-party/parallel-hashmap/parallel_hashmap/phmap_fwd_decl.h
3rd-party/parallel-hashmap/parallel_hashmap/phmap_utils.h
src/byte_set.h
src/dict.cpp
vasapy/__init__.py
vasapy/dict.py
vasapy.egg-info/PKG-INFO
vasapy.egg-info/SOURCES.txt
vasapy.egg-info/dependency_links.txt
vasapy.egg-info/not-zip-safe
vasapy.egg-info/top_level.txt