Metadata-Version: 1.0
Name: vasapy
Version: 0.0.3
Summary: Vectorized ASsociative Arrays for PYthon
Home-page: https://github.com/cosama/vasapy
Author: Marco Salathe
Author-email: UNKNOWN
License: UNKNOWN
Platform: UNKNOWN
